invenio_records_lom/__init__.py
invenio_records_lom/cli.py
invenio_records_lom/config.py
invenio_records_lom/ext.py
invenio_records_lom/oai.py
invenio_records_lom/proxies.py
invenio_records_lom/views.py
invenio_records_lom/alembic/1dc5abf0e34b_create_invenio_records_lom_tables.py
invenio_records_lom/alembic/3c1ae3770e92_add_missing_columns.py
invenio_records_lom/alembic/84003810e5b1_create_invenio_records_lom_branch.py
invenio_records_lom/alembic/__init__.py
invenio_records_lom/fixtures/__init__.py
invenio_records_lom/fixtures/demo.py
invenio_records_lom/fixtures/tasks.py
invenio_records_lom/records/__init__.py
invenio_records_lom/records/api.py
invenio_records_lom/records/models.py
invenio_records_lom/records/dumpers/__init__.py
invenio_records_lom/records/dumpers/stats.py
invenio_records_lom/records/jsonschemas/__init__.py
invenio_records_lom/records/jsonschemas/lomrecords/lom-v1.0.0.json
invenio_records_lom/records/jsonschemas/lomrecords/records/record-v1.0.0.json
invenio_records_lom/records/mappings/__init__.py
invenio_records_lom/records/mappings/os-v2/__init__.py
invenio_records_lom/records/mappings/os-v2/lomrecords/drafts/draft-v1.0.0.json
invenio_records_lom/records/mappings/os-v2/lomrecords/records/record-v1.0.0.json
invenio_records_lom/records/statistics/__init__.py
invenio_records_lom/records/statistics/api.py
invenio_records_lom/records/statistics/templates/__init__.py
invenio_records_lom/records/statistics/templates/aggregations/__init__.py
invenio_records_lom/records/statistics/templates/aggregations/aggr_lom_file_download/__init__.py
invenio_records_lom/records/statistics/templates/aggregations/aggr_lom_file_download/os-v2/__init__.py
invenio_records_lom/records/statistics/templates/aggregations/aggr_lom_file_download/os-v2/aggr-lom-file-download-v1.0.0.json
invenio_records_lom/records/statistics/templates/aggregations/aggr_lom_record_view/__init__.py
invenio_records_lom/records/statistics/templates/aggregations/aggr_lom_record_view/os-v2/__init__.py
invenio_records_lom-0.19.4.dist-info/licenses/AUTHORS.rst
invenio_records_lom-0.19.4.dist-info/licenses/LICENSE
invenio_records_lom-0.19.4.dist-info/METADATA
invenio_records_lom-0.19.4.dist-info/WHEEL
invenio_records_lom-0.19.4.dist-info/entry_points.txt
invenio_records_lom-0.19.4.dist-info/top_level.txt
invenio_records_lom-0.19.4.dist-info/RECORD
