Metadata-Version: 2.4
Name: invenio-records-lom
Version: 0.19.4
Summary: "Invenio data model for Learning Object Metadata."
Home-page: https://github.com/tu-graz-library/invenio-records-lom
Author: "Graz University of Technology"
Author-email: info@tugraz.at
License: MIT
Keywords: invenio record LOM learning object metadata
Platform: any
Classifier: Programming Language :: Python :: 3.12
Classifier: Programming Language :: Python :: 3.13
Classifier: Development Status :: 5 - Production/Stable
Classifier: License :: OSI Approved :: MIT License
Classifier: Operating System :: OS Independent
Classifier: Programming Language :: Python
Classifier: Topic :: Software Development :: Libraries :: Python Modules
Requires-Python: >=3.12
License-File: LICENSE
License-File: AUTHORS.rst
Requires-Dist: invenio-previewer>=1.3.6
Requires-Dist: invenio-rdm-records>=19.0.0
Requires-Dist: invenio-stats>=1.0.0
Requires-Dist: marshmallow>=3.24.0
Provides-Extra: tests
Requires-Dist: invenio-app>=2.0.0; extra == "tests"
Requires-Dist: invenio-cache>=2.0.0; extra == "tests"
Requires-Dist: invenio-db>=2.0.0; extra == "tests"
Requires-Dist: invenio-i18n>=3.0.0; extra == "tests"
Requires-Dist: invenio-search[opensearch2]>=3.0.0; extra == "tests"
Requires-Dist: pytest-black-ng>=0.4.0; extra == "tests"
Requires-Dist: pytest-invenio>=3.0.0; extra == "tests"
Requires-Dist: pytest-mock>=1.6.0; extra == "tests"
Requires-Dist: ruff>=0.4.4; extra == "tests"
Requires-Dist: Sphinx>=4.4.0; extra == "tests"
Requires-Dist: sphinx-autodoc-typehints>=1.10.3; extra == "tests"
Dynamic: license-file
